{
    "title": "Es isch emal es Büebli gsii",
    "genre": "musical",
    "topic": null,
    "source": "Chindermusig",
    "raw_text": [
        "Es isch emal es Büebli gsii\n",
        "\n",
        "Es isch emal es Büebli gsii,\n",
        "wo immer glachet het,\n",
        "vom Morge früeh bis z' Abig spat\n",
        "und au no z' Nacht im Bett:\n",
        "Ha ha ha ha ha ha ha ha ha ha ha ha ha ha!\n",
        "Und wänn mer s Büebli gfröget hät,\n",
        "was lachisch au eso?\n",
        "Häts wiiter glacht und nume gseit:\n",
        "Ich bin halt immer froh!\n",
        "Ha ha ha ha ha ha ha ha ha ha ha ha ha ha!\n",
        "Und luschtig sich's uf dere Wält\n",
        "und lache isch ja gsund\n",
        "und wänn mer immer lache tuet,\n",
        "dänn wird mer chugelirund.\n",
        "Ha ha ha ha ha ha ha ha ha ha ha ha ha ha!\n",
        "\n"
    ],
    "num_lines": 15,
    "num_stanzas": 1,
    "rhyme_scheme": "abcbcdefecghihc",
    "stanza_pattern": "other",
    "ID": 248,
    "region": [
        "unknown"
    ]
}