{
    "title": "Es wollt guet Jegerli jagen ",
    "genre": "narrative",
    "topic": [
        "hunting",
        "love"
    ],
    "source": "Im Röseligarte",
    "raw_text": [
        "Es wollt guet Jegerli jagen\n",
        "\n",
        "Es wollt guet Jegerli jagen\n",
        "Dri Stündelli vor dem Tage\n",
        "Es Hirschelli oder es Reh.\n",
        "\n",
        "Er trieb es auf grüner Weide,\n",
        "Da begenet ihm ein schöns Meitli,\n",
        "Das wollt er haben zur Eh.\n",
        "\n",
        "Er tat es gar freundlich fragen,\n",
        "Ob es ihm well hälfen jagen\n",
        "Es Hirschelli oder es Reh.\n",
        "\n",
        "»Nein, helfen jagen, das tuen i dir nit,\n",
        "Ein andre Bitt abschlag ich Euch nit,\n",
        "Es mege sein, was es well.«\n",
        "\n",
        "Das täte der Jeger verdrießen;\n",
        "Er möchte das Meiteli erschießen\n",
        "Mit sinem geladenen Rohr.\n",
        "\n",
        "Das Meiteli fiel ihm zu Fießen,\n",
        "Er sell es doch nit erschießen,\n",
        "Er sell ihm verziehen die Red\n",
        "\n",
        "Der Jegernahm ein Bedenken,\n",
        "Ob er ihm das Leben well schenken\n",
        "Bis uf ein ander Mal.\n",
        "\n",
        "Sie setzten sich beide zusammen\n",
        "Wohl unter ein grüner Waldtannen\n",
        "Bis luter am hellen Tag.\n",
        "\n",
        "»Stand uf, guet Jegerli balde!\n",
        "Die Sunne steht vor dem Walde,\n",
        "Die Vegelli pfifflen schon.«\n",
        "\n",
        "Sie tät ihn gar freundlich fragen,\n",
        "Ob sie es griens Chrenzli derf tragen\n",
        "Uf ihrem goldgelben Chrushaar.\n",
        "\n",
        "»Es griens Chrenzeli darfst du nit tragen,\n",
        "Es wißes Libli mueßt haben,\n",
        "Wie anderi Frewelli hein.«\n",
        "\n",
        "Etz gab er dem Tiger die Sporen.\n",
        "»Etz han i mis Schätzli verloren,\n",
        "Will balde ein anderes han.«"
    ],
    "num_lines": 47,
    "num_stanzas": 11,
    "rhyme_scheme": "aab",
    "stanza_pattern": "tercets",
    "ID": 22,
    "region": [
        "Bern"
    ]
}